dl_hf_model/__init__.py
dl_hf_model/__main__.py
dl_hf_model/dl_hf_model.py
dl_hf_model-0.1.0a1.dist-info/entry_points.txt
dl_hf_model-0.1.0a1.dist-info/LICENSE
dl_hf_model-0.1.0a1.dist-info/WHEEL
dl_hf_model-0.1.0a1.dist-info/METADATA
dl_hf_model-0.1.0a1.dist-info/RECORD
