Metadata-Version: 2.1
Name: dl-hf-model
Version: 0.1.0a1
Summary: Download and cache a hf model for a given url, save to models dir
Home-page: https://github.com/ffreemt/dl-hf-model
License: MIT
Author: ffreemt
Requires-Python: >=3.10,<4.0
Classifier: License :: OSI Approved :: MIT License
Classifier: Programming Language :: Python :: 3
Classifier: Programming Language :: Python :: 3.10
Requires-Dist: huggingface-hub (>=0.16.4,<0.17.0)
Requires-Dist: install (>=1.3.5,<2.0.0)
Requires-Dist: loguru (>=0.7.0,<0.8.0)
Requires-Dist: set-loglevel (>=0.1.2,<0.2.0)
Requires-Dist: typer (>=0.4.1,<0.5.0)
Project-URL: Repository, https://github.com/ffreemt/dl-hf-model
